MyDatabase/ZLDb.py
MyDatabase/__init__.py
dataAsync-0.2.0.dist-info/METADATA
dataAsync-0.2.0.dist-info/WHEEL
dataAsync-0.2.0.dist-info/top_level.txt
dataAsync-0.2.0.dist-info/RECORD
