Metadata-Version: 2.1
Name: dataAsync
Version: 0.2.0
Summary: async data to sqlalchemy
Home-page: https://github.com/yourusername/your-package
Author: qiaokuoyuan
Author-email: 457361577@qq.com
Classifier: Programming Language :: Python :: 3
Classifier: License :: OSI Approved :: MIT License
Classifier: Operating System :: OS Independent
Requires-Python: >=3.6
Requires-Dist: cx-Oracle>=8.3.0
Requires-Dist: oracledb
Requires-Dist: sqlalchemy
Requires-Dist: pandas
Requires-Dist: pymysql
